GladSpamBot/__init__.py
GladSpamBot/__main__.py
GladSpamBot-0.0.61.dist-info/Licence.txt
GladSpamBot-0.0.61.dist-info/METADATA
GladSpamBot-0.0.61.dist-info/WHEEL
GladSpamBot-0.0.61.dist-info/top_level.txt
GladSpamBot-0.0.61.dist-info/RECORD
