Metadata-Version: 2.1
Name: GladSpamBot
Version: 0.0.61
Summary: Module to log into 20 bots with bot token no memory lock issue!
Home-page: https://github.com/Gladiators-Projects
Author: Gladiators-Projects
Author-email: gladiatorsprojects@gmail.com
License: UNKNOWN
Keywords: Gladiators,SpamBot,spammerbots,GladSpamBot,Gladiators-Projects,SpamBot
Platform: UNKNOWN
Classifier: Programming Language :: Python :: 3
Classifier: Operating System :: OS Independent
Classifier: License :: OSI Approved :: MIT License
Classifier: Intended Audience :: Developers
License-File: Licence.txt
Requires-Dist: heroku3 (==5.1.4)
Requires-Dist: telethon (==1.23.0)
Requires-Dist: gitpython (==3.1.18)
Requires-Dist: python-decouple (==3.4)
Requires-Dist: sqlalchemy (==1.3.20)
Requires-Dist: cryptg
Requires-Dist: psycopg2 (==2.9.1)
